README.md
setup.py
namestand/__init__.py
namestand/converters.py
namestand/patterns.py
namestand/utils.py
namestand.egg-info/PKG-INFO
namestand.egg-info/SOURCES.txt
namestand.egg-info/dependency_links.txt
namestand.egg-info/namespace_packages.txt
namestand.egg-info/not-zip-safe
namestand.egg-info/top_level.txt
test/test_basic.py