Metadata-Version: 1.1
Name: namestand
Version: 0.1.1
Summary: Standardize any list of strings, but especially database/CSV column-names.
Home-page: http://github.com/buzzfeednews/namestand/
Author: Jeremy Singer-Vine
Author-email: jeremy.singer-vine@buzzfeed.com
License: MIT
Keywords: rename columns standardize standardizing names
Platform: UNKNOWN
Classifier: Development Status :: 3 - Alpha
Classifier: Intended Audience :: Developers
Classifier: License :: OSI Approved :: MIT License
Classifier: Operating System :: OS Independent
Classifier: Programming Language :: Python :: 2.6
Classifier: Programming Language :: Python :: 2.7
Classifier: Programming Language :: Python :: 3.1
Classifier: Programming Language :: Python :: 3.4
